{
    "x": [],
    "y": [
        5513.55219,
        5513.56313,
        5513.52935,
        5513.53057,
        5513.52907,
        5513.52398,
        5513.47842,
        5513.41831,
        5513.44776,
        5513.48068,
        5513.50906,
        5513.50963,
        5513.55027,
        5513.53548,
        5513.51674,
        5513.51313,
        5513.50191,
        5513.45442,
        5513.44534,
        5513.44173,
        5513.41525,
        5513.44555
    ],
    "raw_x": [],
    "raw_y": [],
    "x_label": "X-axis",
    "y_label": "Resistance (Ohm)",
    "info": "",
    "custom_name": ""
}